odoo10_addon_mrp_mto_with_stock-10.0.1.0.1-py2.7-nspkg.pth
odoo/addons/mrp_mto_with_stock/README.rst
odoo/addons/mrp_mto_with_stock/__init__.py
odoo/addons/mrp_mto_with_stock/__manifest__.py
odoo/addons/mrp_mto_with_stock/demo/product.xml
odoo/addons/mrp_mto_with_stock/i18n/ca.po
odoo/addons/mrp_mto_with_stock/i18n/de.po
odoo/addons/mrp_mto_with_stock/i18n/es.po
odoo/addons/mrp_mto_with_stock/i18n/es_MX.po
odoo/addons/mrp_mto_with_stock/i18n/fi.po
odoo/addons/mrp_mto_with_stock/i18n/fr.po
odoo/addons/mrp_mto_with_stock/i18n/fr_CH.po
odoo/addons/mrp_mto_with_stock/i18n/gl.po
odoo/addons/mrp_mto_with_stock/i18n/hr.po
odoo/addons/mrp_mto_with_stock/i18n/hr_HR.po
odoo/addons/mrp_mto_with_stock/i18n/it.po
odoo/addons/mrp_mto_with_stock/i18n/lt.po
odoo/addons/mrp_mto_with_stock/i18n/mrp_mto_with_stock.pot
odoo/addons/mrp_mto_with_stock/i18n/nl_NL.po
odoo/addons/mrp_mto_with_stock/i18n/pt_BR.po
odoo/addons/mrp_mto_with_stock/i18n/ro.po
odoo/addons/mrp_mto_with_stock/i18n/sl.po
odoo/addons/mrp_mto_with_stock/i18n/tr.po
odoo/addons/mrp_mto_with_stock/i18n/tr_TR.po
odoo/addons/mrp_mto_with_stock/i18n/vi_VN.po
odoo/addons/mrp_mto_with_stock/i18n/zh_CN.po
odoo/addons/mrp_mto_with_stock/models/__init__.py
odoo/addons/mrp_mto_with_stock/models/mrp_production.py
odoo/addons/mrp_mto_with_stock/models/product_template.py
odoo/addons/mrp_mto_with_stock/models/stock_warehouse.py
odoo/addons/mrp_mto_with_stock/static/description/icon.png
odoo/addons/mrp_mto_with_stock/tests/__init__.py
odoo/addons/mrp_mto_with_stock/tests/test_mrp_mto_with_stock.py
odoo/addons/mrp_mto_with_stock/views/product_template_view.xml
odoo/addons/mrp_mto_with_stock/views/stock_warehouse.xml
odoo10_addon_mrp_mto_with_stock-10.0.1.0.1.dist-info/METADATA
odoo10_addon_mrp_mto_with_stock-10.0.1.0.1.dist-info/RECORD
odoo10_addon_mrp_mto_with_stock-10.0.1.0.1.dist-info/WHEEL
odoo10_addon_mrp_mto_with_stock-10.0.1.0.1.dist-info/namespace_packages.txt
odoo10_addon_mrp_mto_with_stock-10.0.1.0.1.dist-info/top_level.txt
